{
	"display": {
		"title": {
			"text": "The Stealthiest Bonfire Around"
		},
		"description": {
			"text": "Sneak while on fire."
		},
		"icon": {
			"item": "minecraft:black_banner",
			"nbt": "{BlockEntityTag:{Patterns:[{Pattern:moj,Color:1},{Pattern:bri,Color:15},{Pattern:bt,Color:1},{Pattern:mr,Color:15},{Pattern:gru,Color:1},{Pattern:bts,Color:4},{Pattern:gra,Color:7}]}}"
		},
		"frame": "task",
		"show_toast": true,
		"announce_to_chat": true,
		"hidden": false
	},
	"criteria": {
		"Be On Fire": {
			"trigger": "minecraft:location",
			"conditions": {
				"player": {
					"flags": {
						"is_on_fire": true,
						"is_sneaking": true
					}
				}
			}
		}
	},
	"parent": "bingo-bongo-bong:root"
}
